aptx_neuron/__init__.py
aptx_neuron-0.0.3.dist-info/METADATA
aptx_neuron-0.0.3.dist-info/WHEEL
aptx_neuron-0.0.3.dist-info/top_level.txt
aptx_neuron-0.0.3.dist-info/RECORD
