Metadata-Version: 2.4
Name: aptx_neuron
Version: 0.0.3
Summary: A PyTorch implementation of the APTx Neuron.
Home-page: https://github.com/mr-ravin/aptx_neuron
Author: Ravin Kumar
Author-email: mr.ravin_kumar@hotmail.com
License: MIT
Keywords: APTx Neuron,unified neuron,neuron,activation function,deep learning,pytorch,neural network,perceptronmachine learning,artificial intelligence,AI,ML,DL,torch
Classifier: Programming Language :: Python :: 3
Classifier: License :: OSI Approved :: MIT License
Classifier: Operating System :: OS Independent
Classifier: Topic :: Scientific/Engineering :: Artificial Intelligence
Classifier: Intended Audience :: Developers
Classifier: Intended Audience :: Science/Research
Requires-Python: >=3.7
Requires-Dist: torch>=1.8.0
Dynamic: author
Dynamic: author-email
Dynamic: classifier
Dynamic: description
Dynamic: description-content-type
Dynamic: home-page
Dynamic: keywords
Dynamic: license
Dynamic: requires-dist
Dynamic: requires-python
Dynamic: summary
